malo/__init__.py
malo-0.0.0a1.dist-info/METADATA
malo-0.0.0a1.dist-info/WHEEL
malo-0.0.0a1.dist-info/RECORD
